aiomarzban/__init__.py
aiomarzban/api.py
aiomarzban/enums.py
aiomarzban/exceptions.py
aiomarzban/models.py
aiomarzban/utils.py
tests/__init__.py
tests/checker.py
tests/conftest.py
tests/final.py
tests/test_admin.py
tests/test_core.py
tests/test_node.py
tests/test_subscription.py
tests/test_system.py
tests/test_user.py
tests/test_user_template.py
aiomarzban-1.0.3.dist-info/LICENSE
aiomarzban-1.0.3.dist-info/METADATA
aiomarzban-1.0.3.dist-info/WHEEL
aiomarzban-1.0.3.dist-info/top_level.txt
aiomarzban-1.0.3.dist-info/RECORD
