Metadata-Version: 2.2
Name: aiomarzban
Version: 1.0.3
Summary: User-friendly async SDK for the Marzban API.
Home-page: https://github.com/P1nk-L0rD/aiomarzban
Author: P1nk_L0rd
Author-email: mestepanik@gmail.com
Project-URL: Homepage, https://github.com/P1nk-L0rD/aiomarzban
Project-URL: Source, https://github.com/P1nk-L0rD/aiomarzban
Project-URL: Developer, https://t.me/IMC_tech
Keywords: aiomarzban,marzban,marzban API,marzban SDK,Gozargah,marzpy,marz
Classifier: Programming Language :: Python :: 3.10
Classifier: License :: OSI Approved :: MIT License
Classifier: Operating System :: OS Independent
Requires-Python: >=3.9
License-File: LICENSE
Requires-Dist: aiohttp>=3.7.3
Requires-Dist: pydantic>=2.0
Requires-Dist: datetime>=4.0
Dynamic: author
Dynamic: author-email
Dynamic: classifier
Dynamic: description
Dynamic: description-content-type
Dynamic: home-page
Dynamic: keywords
Dynamic: project-url
Dynamic: requires-dist
Dynamic: requires-python
Dynamic: summary
